Library_TrialBasis_FirstTime/__init__.py
Library_TrialBasis-0.1.dist-info/METADATA
Library_TrialBasis-0.1.dist-info/WHEEL
Library_TrialBasis-0.1.dist-info/top_level.txt
Library_TrialBasis-0.1.dist-info/RECORD
