Metadata-Version: 2.1
Name: Library-TrialBasis
Version: 0.1
Summary: Trial Pacakage
Author: Atharva Mandar Phatak
Author-email: 
Classifier: Programming Language :: Python :: 3
Classifier: License :: OSI Approved :: MIT License
Classifier: Operating System :: OS Independent
